Metadata-Version: 1.1
Name: bottleapp
Version: 0.0.1
Summary: Object-oriented extension to bottle, allowing your app to be a class instance and providing automatic path generation.
Home-page: https://github.com/lainproliant/bottleapp
Author: Lain Supe (lainproliant)
Author-email: lainproliant@gmail.com
License: BSD
Keywords: bottle oop web
Platform: UNKNOWN
Classifier: Development Status :: 3 - Alpha
Classifier: Intended Audience :: Developers
Classifier: Framework :: Bottle
Classifier: License :: OSI Approved :: BSD License
Classifier: Topic :: Internet :: WWW/HTTP :: HTTP Servers
Classifier: Programming Language :: Python :: 3.5
Classifier: Programming Language :: Python :: 3.6
